signalfx_detector_syncer/__init__.py
signalfx_detector_syncer/__main__.py
signalfx_detector_syncer/syncer.py
signalfx_detector_syncer/version.py
signalfx_detector_syncer-0.9.dist-info/DESCRIPTION.rst
signalfx_detector_syncer-0.9.dist-info/METADATA
signalfx_detector_syncer-0.9.dist-info/RECORD
signalfx_detector_syncer-0.9.dist-info/WHEEL
signalfx_detector_syncer-0.9.dist-info/entry_points.txt
signalfx_detector_syncer-0.9.dist-info/metadata.json
signalfx_detector_syncer-0.9.dist-info/top_level.txt
signalfx_detector_syncer-0.9.dist-info/zip-safe
