Metadata-Version: 2.0
Name: signalfx-detector-syncer
Version: 0.9
Summary: SignalFx detector sync utility
Home-page: https://github.com/signalfx/signalfx-detector-syncer
Author: SignalFx, Inc
Author-email: info@signalfx.com
License: Apache Software License v2
Platform: UNKNOWN
Classifier: Operating System :: OS Independent
Classifier: Programming Language :: Python
Requires-Dist: PyYAML
Requires-Dist: signalfx (>=1.0.13)
